makeitlitt/__init__.py
makeitlitt/__main__.py
makeitlitt/generate.py
makeitlitt/stackoverflow.py
makeitlitt-0.1.0.dist-info/LICENSE
makeitlitt-0.1.0.dist-info/METADATA
makeitlitt-0.1.0.dist-info/WHEEL
makeitlitt-0.1.0.dist-info/top_level.txt
makeitlitt-0.1.0.dist-info/RECORD
